struvolpy/Structure.py
struvolpy/Volume.py
struvolpy/__init__.py
struvolpy/wrappers/__init__.py
struvolpy/wrappers/wrappers.py
struvolpy-1.0.9.dist-info/LICENSE.txt
struvolpy-1.0.9.dist-info/METADATA
struvolpy-1.0.9.dist-info/WHEEL
struvolpy-1.0.9.dist-info/top_level.txt
struvolpy-1.0.9.dist-info/RECORD
