Metadata-Version: 2.1
Name: struvolpy
Version: 1.0.9
Summary: "A python package for parsing atomic coordinates files and electron density maps"
Home-page: https://github.com/hllelli2/struvolpy/
Author: Luc Elliott
Author-email: hllelli2@liverpool.ac.uk
License: "BSD-3-Clause"
Classifier: Programming Language :: Python :: 3.7
Classifier: Programming Language :: Python :: 3.8
Classifier: Programming Language :: Python :: 3.9
Classifier: License :: OSI Approved :: GNU General Public License v3 (GPLv3)
Classifier: Operating System :: OS Independent
Requires-Python: >=3.7
License-File: LICENSE.txt
Requires-Dist: numpy (>=1.21.6)
Requires-Dist: mrcfile (>=1.4.3)
Requires-Dist: gemmi (>=0.4.5)
Requires-Dist: scikit-learn (>=1.0.2)
Provides-Extra: tempy
Requires-Dist: biotempy ; extra == 'tempy'
